miv/__init__.py
miv/import_helper.py
miv/plugins.py
miv/py.typed
miv/typing.py
miv/core/__init__.py
miv/core/pipeline.py
miv/core/protocol.py
miv/core/readme.md
miv/core/datatype/__init__.py
miv/core/datatype/events.py
miv/core/datatype/pure_python.py
miv/core/datatype/signal.py
miv/core/datatype/spikestamps.py
miv/core/datatype/operation/__init__.py
miv/core/datatype/operation/concatenate.py
miv/core/operator/cachable.py
miv/core/operator/callback.py
miv/core/operator/chainable.py
miv/core/operator/loggable.py
miv/core/operator/operator.py
miv/core/operator/policy.py
miv/core/operator/protocol.py
miv/core/operator/wrapper.py
miv/core/operator_generator/callback.py
miv/core/operator_generator/operator.py
miv/core/operator_generator/policy.py
miv/core/operator_generator/wrapper.py
miv/core/utils/__init__.py
miv/core/utils/graph_sorting.py
miv/datasets/__init__.py
miv/datasets/criticality.py
miv/datasets/openephys_sample.py
miv/datasets/optogenetic.py
miv/datasets/protocol.py
miv/datasets/ttl_events.py
miv/datasets/utils.py
miv/experimental/automatic_channel_masking/module.py
miv/io/__init__.py
miv/io/protocol.py
miv/io/asdf/__init__.py
miv/io/asdf/asdf.py
miv/io/file/__init__.py
miv/io/file/import_signal.py
miv/io/file/read.py
miv/io/file/write.py
miv/io/intan/__init__.py
miv/io/intan/data.py
miv/io/intan/rhs.py
miv/io/openephys/__init__.py
miv/io/openephys/binary.py
miv/io/openephys/data.py
miv/io/serial/__init__.py
miv/io/serial/arduino.py
miv/io/serial/stimjim.py
miv/io/simulator/__init__.py
miv/io/simulator/data.py
miv/machinary/README.md
miv/machinary/clean_cache.py
miv/machinary/convert_open_ephys_to_miv.py
miv/machinary/miv_extract_spiketrain.py
miv/machinary/zip_results.py
miv/mea/__init__.py
miv/mea/_convert512.py
miv/mea/_convert_128_rhs_rhd.py
miv/mea/_convert_64_rhd_to_rhs.py
miv/mea/_draw.py
miv/mea/_oe_mapping.py
miv/mea/_register_electrodes.py
miv/mea/base.py
miv/mea/channel_mapping.py
miv/mea/core.py
miv/mea/export.py
miv/mea/grid.py
miv_os-0.3.3.dist-info/METADATA
miv_os-0.3.3.dist-info/WHEEL
miv_os-0.3.3.dist-info/entry_points.txt
miv_os-0.3.3.dist-info/licenses/LICENSE
miv_os-0.3.3.dist-info/RECORD
