Metadata-Version: 2.4
Name: MiV-OS
Version: 0.3.3
Summary: Python software for analysis and computing framework used in MiV project.
Project-URL: Homepage, https://mindinvitro.illinois.edu
Project-URL: Documentation, https://miv-os.readthedocs.io
Project-URL: Repository, https://github.com/GazzolaLab/MiV-OS
Author-email: skim0119 <skim0119@gmail.com>
License: MIT
License-File: LICENSE
Keywords: data-analysis,electrophysiology,neurophysiology,neuroscience,statistics
Classifier: Development Status :: 4 - Beta
Classifier: Intended Audience :: Education
Classifier: Intended Audience :: Science/Research
Classifier: License :: OSI Approved :: MIT License
Classifier: Operating System :: OS Independent
Classifier: Programming Language :: Python :: 3
Classifier: Programming Language :: Python :: 3.10
Classifier: Programming Language :: Python :: 3.11
Classifier: Programming Language :: Python :: 3.12
Requires-Python: <=3.12,>=3.10
Requires-Dist: click>=8.1.3
Requires-Dist: coverage>=7.1.0
Requires-Dist: elephant>=1.0.0
Requires-Dist: graphviz>=0.20.1
Requires-Dist: h5py>=3.7.0
Requires-Dist: joblib>=1.4.2
Requires-Dist: machinable>=4.0
Requires-Dist: matplotlib>=3.5.2
Requires-Dist: meautility>=1.5.1
Requires-Dist: mpi4py>=4.0.3
Requires-Dist: neo<0.14.0,>=0.11.0
Requires-Dist: numba>=0.58.1
Requires-Dist: numpy>=1.23.2
Requires-Dist: opencv-python>=4.7.0.72
Requires-Dist: pandas>=2.0.2
Requires-Dist: pillow==10.3.0
Requires-Dist: pyinform>=0.2.0
Requires-Dist: pytest>=8.3.5
Requires-Dist: pyvis<0.4.0,>=0.2.1
Requires-Dist: pywavelets>=1.3.0
Requires-Dist: quantities>=0.14.1
Requires-Dist: scikit-learn>=1.1.1
Requires-Dist: scipy>=1.9.1
Requires-Dist: seaborn<0.13.0,>=0.11.2
Requires-Dist: tqdm>=4.64.0
Requires-Dist: viziphant>=0.4.0
Provides-Extra: algorithmextension
Requires-Dist: rupture>=1.4.5; extra == 'algorithmextension'
Provides-Extra: dev
Requires-Dist: coverage[toml]>=7.5.3; extra == 'dev'
Requires-Dist: mypy-extensions>=1.0.0; extra == 'dev'
Requires-Dist: mypy>=1.12.1; extra == 'dev'
Requires-Dist: pre-commit>=3.0.4; extra == 'dev'
Requires-Dist: pydocstyle>=6.1.1; extra == 'dev'
Requires-Dist: pytest-cov>=5.0.0; extra == 'dev'
Requires-Dist: pytest-html>=4.1.0; extra == 'dev'
Requires-Dist: pytest-mock>=3.14.0; extra == 'dev'
Requires-Dist: pytest-mpi>=0.6; extra == 'dev'
Requires-Dist: pytest>=8.3.3; extra == 'dev'
Requires-Dist: ruff>=0.3.4; extra == 'dev'
Provides-Extra: docs
Requires-Dist: myst-nb>=0.17.1; extra == 'docs'
Requires-Dist: myst-parser>=0.18.1; extra == 'docs'
Requires-Dist: numpydoc>=1.4.0; extra == 'docs'
Requires-Dist: pydata-sphinx-theme>=0.14; extra == 'docs'
Requires-Dist: readthedocs-sphinx-search>=0.3.1; extra == 'docs'
Requires-Dist: sphinx-autodoc-typehints>=1.19.1; extra == 'docs'
Requires-Dist: sphinx-copybutton>=0.5.0; extra == 'docs'
Requires-Dist: sphinx-togglebutton>=0.3.2; extra == 'docs'
Requires-Dist: sphinx>=5.3.0; extra == 'docs'
Requires-Dist: sphinxcontrib-mermaid>=1.0.0; extra == 'docs'
Provides-Extra: experiment
Requires-Dist: pyserial>=3.5; extra == 'experiment'
Provides-Extra: mpi
Requires-Dist: mpi4py>=4.0.1; extra == 'mpi'
Provides-Extra: sortingextension
Requires-Dist: dtaidistance>=2.3.10; extra == 'sortingextension'
